LICENSE.txt
MANIFEST.in
README.md
pyproject.toml
setup.cfg
setup.py
btrievePython/__init__.py
btrievePython/btrieveC.h
btrievePython/btrieveCpp.h
btrievePython/btrievePython.cpp
btrievePython.egg-info/PKG-INFO
btrievePython.egg-info/SOURCES.txt
btrievePython.egg-info/dependency_links.txt
btrievePython.egg-info/top_level.txt
btrievePython/win32/btrieveCpp.lib
btrievePython/win64/btrieveCpp.lib