Metadata-Version: 2.4
Name: btrievePython
Version: 16.10.30.0b0
Summary: Btrieve Python provides a Client API for Actian Zen
Home-page: https://www.actian.com/databases/zen
Author: Actian Corporation
Author-email: community.admin@actian.com
License: ﻿Actian Corporation
Project-URL: Homepage, https://www.actian.com/databases/zen
Project-URL: Product Forum, https://communities.actian.com/s/actian-zen
Project-URL: Documentation, https://docs.actian.com/zen
Project-URL: Download Actian Zen, https://esd.actian.com/product
Classifier: License :: Other/Proprietary License
Classifier: Operating System :: Microsoft :: Windows
Classifier: Operating System :: POSIX :: Linux
Classifier: Programming Language :: C++
Classifier: Programming Language :: Python :: 3
Requires-Python: >=3.7
License-File: LICENSE.txt
Dynamic: license-file
